flex_motion/__init__.py
flex_motion/_flex_motion_cffi.c
flex_motion/_flex_motion_cffi.cp37-win32.pyd
flex_motion/compile_flex_motion.py
flex_motion/flex_config.py
flex_motion/flex_motion.py
flex_motion/flex_motion_low_level.py
flex_motion/version.py
flex_motion/Release/_flex_motion_cffi.cp37-win32.exp
flex_motion/Release/_flex_motion_cffi.cp37-win32.lib
flex_motion/Release/_flex_motion_cffi.obj
flex_motion/example_configs/two_stepper_config.toml
flex_motion/lib/FlexMS32.lib
flex_motion/lib/MotnCnst.h
flex_motion/lib/MotnErr.bas
flex_motion/lib/MotnErr.h
flex_motion/lib/flexmotn.h
flex_motion/lib/flexmotn_flat.h
flex_motion/lib/nimcBasicTypes.h
flex_motion-0.0.1.dist-info/LICENSE
flex_motion-0.0.1.dist-info/METADATA
flex_motion-0.0.1.dist-info/WHEEL
flex_motion-0.0.1.dist-info/top_level.txt
flex_motion-0.0.1.dist-info/RECORD
