Metadata-Version: 2.1
Name: flex-motion
Version: 0.0.1
Summary: Python bindings around National Instruments's Flex Motion
Home-page: https://github.com/chstan/py-flex-motion
Author: Conrad Stansbury
Author-email: chstansbury@gmail.com
License: UNKNOWN
Platform: UNKNOWN
Classifier: Development Status :: 3 - Alpha
Classifier: Intended Audience :: Science/Research
Classifier: Intended Audience :: Developers
Classifier: License :: OSI Approved :: GNU General Public License v3 or later (GPLv3+)
Classifier: Programming Language :: Python
Classifier: Programming Language :: Python :: 3
Classifier: Programming Language :: Python :: 3.7
Classifier: Programming Language :: Python :: Implementation :: CPython
Classifier: Natural Language :: English
Classifier: Operating System :: Microsoft :: Windows :: Windows 7
Classifier: Operating System :: Microsoft :: Windows :: Windows 8
Classifier: Operating System :: Microsoft :: Windows :: Windows 10
Classifier: Topic :: Scientific/Engineering
Classifier: Topic :: Software Development :: Libraries :: Python Modules
Requires-Python: >=3.7.0
Requires-Dist: setuptools
Requires-Dist: cffi
Requires-Dist: toml
Provides-Extra: rest
Requires-Dist: Sphinx ; extra == 'rest'
